[{
        "category": "Java",
        "created_at": "2020-04-18",
        "articles": [{
                "title": "测试文档1",
                "url": "/Java/测试文档1.md",
                "created_at": "2020-04-18 16:23:12"
            },
            {
                "title": "测试文档2",
                "url": "/Java/测试文档2.md",
                "created_at": "2020-04-18 16:45:12"
            }
        ]
    },
    {
        "category": "数据库",
        "created_at": "2020-04-09",
        "articles": [{
            "title": "Mybatis 项目搭建 (IDEA)",
            "url": "/数据库/Mybatis 项目搭建 (IDEA).md",
            "created_at": "2020-04-09 12:00:35"
        }]
    },
    {
        "category": "服务器",
        "created_at": "2020-02-12",
        "articles": [{
            "title": "Ubuntu 18.04.4 LTS 环境使用 Linux 二进制文件 (x64) 安装 Node.js",
            "url": "/服务器/Ubuntu 18.04.4 LTS 环境使用 Linux 二进制文件 (x64) 安装 Node.js.md",
            "created_at": "2020-02-12 18:06:47"
        }]
    }
]